__init__.py
main.py
gardena/__init__.py
gardena/_version.py
gardena/base_gardena_class.py
gardena/location.py
gardena/smart_system.py
gardena/token_manager.py
gardena/devices/__init__.py
gardena/devices/base_device.py
gardena/devices/device_factory.py
gardena/devices/mower.py
gardena/devices/power_socket.py
gardena/devices/sensor.py
gardena/devices/smart_irrigation_control.py
gardena/devices/soil_sensor.py
gardena/devices/water_control.py
gardena/exceptions/__init__.py
gardena/exceptions/authentication_exception.py
py_smart_gardena-1.3.17.dist-info/LICENSE
py_smart_gardena-1.3.17.dist-info/METADATA
py_smart_gardena-1.3.17.dist-info/WHEEL
py_smart_gardena-1.3.17.dist-info/top_level.txt
py_smart_gardena-1.3.17.dist-info/RECORD
