Metadata-Version: 2.1
Name: py-smart-gardena
Version: 1.3.17
Summary: This library aims to provide python way to communicate with gardena smart gateway and all smart gardena systems.
Home-page: https://github.com/grm/py-smart-gardena
Author: Jérémie Klein
Author-email: grm.klein@gmail.com
License: MIT
Classifier: Programming Language :: Python :: 3
Classifier: License :: OSI Approved :: MIT License
Classifier: Operating System :: OS Independent
License-File: LICENSE
Requires-Dist: requests
Requires-Dist: websockets
Requires-Dist: httpx
Requires-Dist: oauthlib
Requires-Dist: authlib
Requires-Dist: backoff
Provides-Extra: test
Requires-Dist: pytest>=6.0; extra == "test"
Requires-Dist: coverage; extra == "test"
Requires-Dist: pytest-cov; extra == "test"
Requires-Dist: requests_mock; extra == "test"
Provides-Extra: dev
Requires-Dist: pre-commit; extra == "dev"
